{
  "armies": [
    {
      "id": 1,
      "name": "Barbarian Warband",
      "units": []
    },
    {
      "id": 2,
      "name": "Beastman Warband",
      "units": []
    },
    {
      "id": 3,
      "name": "Dwarf Warband",
      "units": []
    },
    {
      "id": 4,
      "name": "Elf Warband",
      "units": [
        {
          "id": 0,
          "name": "Elven Lord",
          "point_value": "108",
          "type": "Warlord Warrior Unit",
          "stats": [
            {
              "ammount": "x",
              "name": "x",
              "weapon": [],
              "ag": "x",
              "acc": "x",
              "str": "x",
              "res": "x",
              "init": "x",
              "co": "9",
              "special": []
            },
            {
              "ammount": "x",
              "name": "x",
              "weapon": [],
              "ag": "x",
              "acc": "x",
              "str": "x",
              "res": "x",
              "init": "x",
              "co": "x",
              "special": []
            },
            {
              "ammount": "x",
              "name": "x",
              "weapon": [],
              "ag": "x",
              "acc": "x",
              "str": "x",
              "res": "x",
              "init": "x",
              "co": "x",
              "special": []
            },
            {
              "ammount": "x",
              "name": "x",
              "weapon": [],
              "ag": "x",
              "acc": "x",
              "str": "x",
              "res": "x",
              "init": "x",
              "co": "x",
              "special": []
            },
            {
              "ammount": "x",
              "name": "x",
              "weapon": [],
              "ag": "x",
              "acc": "x",
              "str": "x",
              "res": "x",
              "init": "x",
              "co": "x",
              "special": []
            }
          ],
          "options": [
            {
              "text": "x",
              "type": "one_time",
              "cost": "x",
              "max": "x"
            },
            {
              "text": "x",
              "type": "one_time",
              "cost": "x",
              "max": "x"
            },
            {
              "text": "x",
              "type": "one_time",
              "cost": "x",
              "max": "x"
            },
            {
              "text": "x",
              "type": "one_time",
              "cost": "x",
              "max": "x"
            },
            {
              "text": "x",
              "type": "one_time",
              "cost": "x",
              "max": "x"
            },
            {
              "text": "x",
              "type": "one_time",
              "cost": "x",
              "max": "x"
            },
            {
              "text": "x",
              "type": "one_time",
              "cost": "x",
              "max": "x"
            },
            {
              "text": "x",
              "type": "one_time",
              "cost": "x",
              "max": "x"
            },
            {
              "text": "x",
              "type": "one_time",
              "cost": "x",
              "max": "x"
            },
            {
              "text": "x",
              "type": "one_time",
              "cost": "x",
              "max": "x"
            }
          ]
        },
        {
          "id": 1,
          "name": "Mounted Elven Lord",
          "point_value": "undefined",
          "type": "undefined",
          "stats": [
            {
              "ammount": "x",
              "name": "x",
              "weapon": [],
              "ag": "x",
              "acc": "x",
              "str": "x",
              "res": "x",
              "init": "x",
              "co": "x",
              "special": ""
            },
            {
              "ammount": "x",
              "name": "x",
              "weapon": [],
              "ag": "x",
              "acc": "x",
              "str": "x",
              "res": "x",
              "init": "x",
              "co": "x",
              "special": ""
            },
            {
              "ammount": "x",
              "name": "x",
              "weapon": [
                "weapons.melee.1",
                "weapons.melee.0"
              ],
              "ag": "x",
              "acc": "x",
              "str": "x",
              "res": "x",
              "init": "x",
              "co": "x",
              "special": [
                "skills.0"
              ]
            },
            {
              "ammount": "x",
              "name": "x",
              "weapon": [],
              "ag": "x",
              "acc": "x",
              "str": "x",
              "res": "x",
              "init": "x",
              "co": "x",
              "special": ""
            },
            {
              "ammount": "x",
              "name": "x",
              "weapon": [],
              "ag": "x",
              "acc": "x",
              "str": "x",
              "res": "x",
              "init": "x",
              "co": "x",
              "special": ""
            }
          ]
        }
      ]
    },
    {
      "id": 5,
      "name": "Gnoll War Party",
      "units": []
    },
    {
      "id": 6,
      "name": "Goblin Warband",
      "units": []
    },
    {
      "id": 7,
      "name": "Hafling Warband",
      "units": []
    },
    {
      "id": 8,
      "name": "Knightly Warband",
      "units": []
    },
    {
      "id": 9,
      "name": "Olympian Warband",
      "units": []
    },
    {
      "id": 10,
      "name": "Orc Warband",
      "units": []
    },
    {
      "id": 11,
      "name": "Undead Host",
      "units": []
    },
    {
      "id": 12,
      "name": "Monsters",
      "units": []
    }
  ],
  "spells": [
    {
      "id": 0,
      "name": "New spell",
      "effects": "undefinedfasdfsd"
    }
  ],
  "skills": [
    {
      "id": 0,
      "name": "Alied Monster ",
      "effects": "Unaffected by Commander, Hero or Flow rules."
    }
  ],
  "weapons": {
    "melee": [
      {
        "id": 0,
        "name": "Rock",
        "sv": 0,
        "special_rules": "Can also be thrown as range weapon"
      },
      {
        "id": 1,
        "name": "Cudgel or Club",
        "sv": 0,
        "special_rules": "-"
      }
    ],
    "range": [
      {
        "id": 0,
        "name": "Bow",
        "short": "0-10\"",
        "long": "10-20\"",
        "extreme": "-",
        "sv": "0",
        "special_rules": "-"
      }
    ]
  }
}